comfortpy/__init__.py
comfortpy/discomfortmethod.py
comfortpy/main.py
comfortpy/thermaldefinitions.py
comfortpy-0.0.2.dist-info/LICENSE.html
comfortpy-0.0.2.dist-info/METADATA
comfortpy-0.0.2.dist-info/WHEEL
comfortpy-0.0.2.dist-info/top_level.txt
comfortpy-0.0.2.dist-info/RECORD
