Metadata-Version: 2.1
Name: comfortpy
Version: 0.0.2
Summary: Package to calculate thermal discomfort severity under several thermal definitions (e.g. traditional thermal comfort, sleep comfort, occupant health and safety limits, etc.).
Home-page: https://github.com/sh-s/comfortpy
Author: Shide Salimi
Author-email: shide.salimi@gmail.com
License: UNKNOWN
Platform: UNKNOWN
Classifier: Programming Language :: Python :: 3
Classifier: License :: OSI Approved :: MIT License
Classifier: Operating System :: OS Independent
Requires-Python: >=3.6
Requires-Dist: pythermalcomfort
Requires-Dist: shapely
